README.md
setup.py
lib/candy_board_qws/__init__.py
lib/candy_board_qws.egg-info/PKG-INFO
lib/candy_board_qws.egg-info/SOURCES.txt
lib/candy_board_qws.egg-info/dependency_links.txt
lib/candy_board_qws.egg-info/top_level.txt