Metadata-Version: 1.1
Name: candy-board-qws
Version: 2.2.0
Summary: Base CANDY LINE boards service for Quectel Wireless Solutions Modules
Home-page: http://github.com/CANDY-LINE/candy-board-qws
Author: Daisuke Baba
Author-email: baba.daisuke@gmail.com
License: ASL 2.0
Download-URL: https://github.com/CANDY-LINE/candy-board-qws/tarball/2.2.0
Keywords: CANDY RED,CANDY EGG,CANDY LINE,CANDY Pi Lite,CANDY Pi Lite+
Platform: UNKNOWN
Classifier: Programming Language :: Python
Classifier: Development Status :: 5 - Production/Stable
Classifier: Natural Language :: English
Classifier: Environment :: Console
Classifier: Intended Audience :: System Administrators
Classifier: Intended Audience :: Developers
Classifier: License :: OSI Approved :: Apache Software License
Classifier: Operating System :: POSIX :: Linux
Classifier: Topic :: System :: Hardware
